stun/__init__.py
stun/cli.py
tests/__init__.py
tests/test_cli.py
pystun3-2.0.0.dist-info/LICENSE
pystun3-2.0.0.dist-info/METADATA
pystun3-2.0.0.dist-info/WHEEL
pystun3-2.0.0.dist-info/entry_points.txt
pystun3-2.0.0.dist-info/top_level.txt
pystun3-2.0.0.dist-info/RECORD
