Metadata-Version: 2.1
Name: pystun3
Version: 2.0.0
Summary: A Python STUN client for getting NAT type and external IP (RFC 3489)
Home-page: http://github.com/talkiq/pystun3
Author: TalkIQ (original authors: gaohawk, Justin Riley)
Author-email: engineering@talkiq.com
License: MIT
Keywords: STUN NAT
Classifier: Development Status :: 4 - Beta
Classifier: License :: OSI Approved :: MIT License
Classifier: Programming Language :: Python :: 2
Classifier: Programming Language :: Python :: 2.7
Classifier: Topic :: Internet
Classifier: Topic :: System :: Networking :: Firewalls
License-File: LICENSE
